Metadata-Version: 1.1
Name: pyautomailer
Version: 0.1
Summary: A fully customizable automatic email client service.
Home-page: http://...
Author: Matteo Cappello
Author-email: matteocappello94@gmail.com
License: MIT
Keywords: automatic email service
Platform: UNKNOWN
Classifier: Development Status :: 2 - Pre-Alpha
Classifier: License :: OSI Approved :: MIT License
Classifier: Programming Language :: Python :: 3.6
Classifier: Topic :: Communications :: Email
Classifier: Natural Language :: English
Classifier: Operating System :: Microsoft :: Windows :: Windows 10
